yt_adl/__init__.py
yt_adl/cli.py
yt_adl-1.0.0.dist-info/LICENSE
yt_adl-1.0.0.dist-info/METADATA
yt_adl-1.0.0.dist-info/WHEEL
yt_adl-1.0.0.dist-info/entry_points.txt
yt_adl-1.0.0.dist-info/top_level.txt
yt_adl-1.0.0.dist-info/RECORD
