Metadata-Version: 2.1
Name: yt-adl
Version: 1.0.0
Summary: YouTube Audio and Video Downloader with advanced features
Home-page: https://x.com/Lanaev0li
Author: Avinion
Author-email: shizofrin@gmail.com
Project-URL: Bug Tracker, https://x.com/Lanaev0li
Classifier: Programming Language :: Python :: 3
Classifier: License :: OSI Approved :: MIT License
Classifier: Operating System :: OS Independent
Requires-Python: >=3.6
License-File: LICENSE
Requires-Dist: yt-dlp
Requires-Dist: colorama
Requires-Dist: tqdm
Requires-Dist: mutagen
Requires-Dist: pydub
